{
  "frames": {
    "reel_shadow.png": {
      "frame": {
        "x": 3,
        "y": 3,
        "w": 287,
        "h": 81
      },
      "rotated": false,
      "trimmed": true,
      "spriteSourceSize": {
        "x": 2,
        "y": 2,
        "w": 287,
        "h": 81
      },
      "sourceSize": {
        "w": 291,
        "h": 85
      },
      "pivot": {
        "x": 0.5,
        "y": 0.5
      }
    },
    "ice_win_2.png": {
      "frame": {
        "x": 3,
        "y": 90,
        "w": 263,
        "h": 268
      },
      "rotated": true,
      "trimmed": true,
      "spriteSourceSize": {
        "x": 16,
        "y": 5,
        "w": 263,
        "h": 268
      },
      "sourceSize": {
        "w": 292,
        "h": 287
      },
      "pivot": {
        "x": 0.5,
        "y": 0.5
      }
    },
    "ice_1.png": {
      "frame": {
        "x": 296,
        "y": 3,
        "w": 266,
        "h": 262
      },
      "rotated": true,
      "trimmed": true,
      "spriteSourceSize": {
        "x": 25,
        "y": 23,
        "w": 266,
        "h": 262
      },
      "sourceSize": {
        "w": 298,
        "h": 322
      },
      "pivot": {
        "x": 0.5,
        "y": 0.5
      }
    },
    "ice_win_1.png": {
      "frame": {
        "x": 3,
        "y": 359,
        "w": 266,
        "h": 263
      },
      "rotated": false,
      "trimmed": true,
      "spriteSourceSize": {
        "x": 25,
        "y": 23,
        "w": 266,
        "h": 263
      },
      "sourceSize": {
        "w": 298,
        "h": 322
      },
      "pivot": {
        "x": 0.5,
        "y": 0.5
      }
    },
    "ice_2.png": {
      "frame": {
        "x": 275,
        "y": 359,
        "w": 262,
        "h": 265
      },
      "rotated": true,
      "trimmed": true,
      "spriteSourceSize": {
        "x": 17,
        "y": 7,
        "w": 262,
        "h": 265
      },
      "sourceSize": {
        "w": 292,
        "h": 287
      },
      "pivot": {
        "x": 0.5,
        "y": 0.5
      }
    }
  },
  "meta": {
    "app": "http://github.com/odrick/free-tex-packer-core",
    "version": "0.3.4",
    "image": "slotMachine.png",
    "format": "RGBA8888",
    "size": {
      "w": 561,
      "h": 625
    },
    "scale": 1
  }
}